pkg_guard/__main__.py
pkg_guard/cli.py
pkg_guard/popular_packages.txt
pkg_guard/core/installer.py
pkg_guard/core/pypi_utils.py
pkg_guard/pkg_guard/__init__.py
pkg_guard/pkg_guard/core/__init__.py
pkg_guard/pkg_guard/ui/__init__.py
pkg_guard/ui/console.py
pkg_guard/ui/prompts.py
pkg_guard-0.1.5.dist-info/licenses/LICENSE
pkg_guard-0.1.5.dist-info/METADATA
pkg_guard-0.1.5.dist-info/WHEEL
pkg_guard-0.1.5.dist-info/entry_points.txt
pkg_guard-0.1.5.dist-info/top_level.txt
pkg_guard-0.1.5.dist-info/RECORD
