Metadata-Version: 2.4
Name: pkg-guard
Version: 0.1.5
Summary: Safe, typo-aware package installer for Python.
Author: Prasad
License: MIT
Project-URL: Homepage, https://github.com/Prasad2357/pkg-guard
Project-URL: Repository, https://github.com/Prasad2357/pkg-guard
Project-URL: BugTracker, https://github.com/Prasad2357/pkg-guard/issues
Requires-Python: >=3.9
License-File: LICENSE
Requires-Dist: typer
Requires-Dist: requests
Requires-Dist: rich
Requires-Dist: InquirerPy
Requires-Dist: rapidfuzz
Requires-Dist: appdirs
Dynamic: license-file
